eats_worm/Curator.py
eats_worm/Extractor.py
eats_worm/FilterSweeper.py
eats_worm/PlotUtils.py
eats_worm/Threads.py
eats_worm/__init__.py
eats_worm/filter_experiment.py
eats_worm/multifiletiff.py
eats_worm-0.0.3.dist-info/LICENSE
eats_worm-0.0.3.dist-info/METADATA
eats_worm-0.0.3.dist-info/WHEEL
eats_worm-0.0.3.dist-info/entry_points.txt
eats_worm-0.0.3.dist-info/top_level.txt
eats_worm-0.0.3.dist-info/RECORD
