Metadata-Version: 2.1
Name: eats-worm
Version: 0.0.3
Summary: Method for extracting GCaMP signal from volumetric imaging recordings
Home-page: 
Author: UCSF FOCO Lab
Author-email: focolabdev@gmail.com
Classifier: Programming Language :: Python :: 3
Classifier: Framework :: napari
Classifier: License :: OSI Approved :: MIT License
Classifier: Operating System :: OS Independent
Requires-Python: <3.11
Requires-Dist: numpy (>=1.22.4)
Requires-Dist: scipy (>=1.0.0)
Requires-Dist: tifffile (>=2022.5.4)
Requires-Dist: opencv-python-headless (>=4.1.0.25)
Requires-Dist: matplotlib (>=2.1.0)
Requires-Dist: foco-improc
Requires-Dist: npex
Requires-Dist: imreg-dft
Requires-Dist: fastcluster
Requires-Dist: napari[all]
Requires-Dist: pyqtgraph (==0.13)
Requires-Dist: magicgui
Requires-Dist: pandas (>=1.4.2)
Requires-Dist: scikit-image
Requires-Dist: xmltodict
Requires-Dist: pynwb
Requires-Dist: nwbinspector
Requires-Dist: dandi
